volt_client_web/__init__.py
volt_client_web/crypto_utils.py
volt_client_web/volt_client.py
volt_client_web/websocket_rpc.py
volt_client_web-0.1.14.dist-info/METADATA
volt_client_web-0.1.14.dist-info/WHEEL
volt_client_web-0.1.14.dist-info/RECORD
