Metadata-Version: 2.1
Name: volt-client-web
Version: 0.1.14
Summary: Python websocket client API
License: UNLISENCED
Author: Ash Setter
Author-email: ash@nquiringminds.com
Requires-Python: >=3.9,<4.0
Classifier: License :: Other/Proprietary License
Classifier: Programming Language :: Python :: 3
Classifier: Programming Language :: Python :: 3.9
Classifier: Programming Language :: Python :: 3.10
Classifier: Programming Language :: Python :: 3.11
Requires-Dist: base58 (>=2.1.1,<3.0.0)
Requires-Dist: cryptography (>=40.0.1,<41.0.0)
Requires-Dist: jsonrpcclient (>=4.0.3,<5.0.0)
Requires-Dist: pyee (>=9.0.4,<10.0.0)
Requires-Dist: pytest-asyncio (>=0.21.0,<0.22.0)
Requires-Dist: websockets (>=11.0.2,<12.0.0)
